Metadata-Version: 2.4
Name: borneo_client_python
Version: 3.19.4
Summary: borneo_client_python client
License: Apache-2.0
Keywords: smithy,borneo_client_python
Classifier: Development Status :: 2 - Pre-Alpha
Classifier: Intended Audience :: Developers
Classifier: Intended Audience :: System Administrators
Classifier: Natural Language :: English
Classifier: License :: OSI Approved :: Apache Software License
Classifier: Programming Language :: Python
Classifier: Programming Language :: Python :: 3
Classifier: Programming Language :: Python :: 3 :: Only
Classifier: Programming Language :: Python :: 3.12
Requires-Python: >=3.12
License-File: LICENSE
Provides-Extra: tests
Requires-Dist: pytest<8.0.0,>=7.2.0; extra == "tests"
Requires-Dist: pytest-asyncio<0.21.0,>=0.20.3; extra == "tests"
Dynamic: license-file
